pgqueuer/__init__.py
pgqueuer/__main__.py
pgqueuer/_version.py
pgqueuer/applications.py
pgqueuer/buffers.py
pgqueuer/cache.py
pgqueuer/cli.py
pgqueuer/completion.py
pgqueuer/db.py
pgqueuer/errors.py
pgqueuer/executors.py
pgqueuer/factories.py
pgqueuer/heartbeat.py
pgqueuer/helpers.py
pgqueuer/listeners.py
pgqueuer/logconfig.py
pgqueuer/models.py
pgqueuer/py.typed
pgqueuer/qb.py
pgqueuer/qm.py
pgqueuer/queries.py
pgqueuer/query_helpers.py
pgqueuer/retries.py
pgqueuer/sm.py
pgqueuer/supervisor.py
pgqueuer/tm.py
pgqueuer/tracing.py
pgqueuer/types.py
pgqueuer-0.25.2.dist-info/licenses/LICENSE
pgqueuer-0.25.2.dist-info/METADATA
pgqueuer-0.25.2.dist-info/WHEEL
pgqueuer-0.25.2.dist-info/entry_points.txt
pgqueuer-0.25.2.dist-info/top_level.txt
pgqueuer-0.25.2.dist-info/RECORD
