Metadata-Version: 2.4
Name: pgqueuer
Version: 0.25.2
Summary: Pgqueuer is a Python library leveraging PostgreSQL for efficient job queuing.
Author: JeyBee
License: MIT License
Project-URL: Documentation, https://github.com/janbjorge/pgqueuer/wiki
Project-URL: Homepage, https://github.com/janbjorge/pgqueuer/
Project-URL: Issues, https://github.com/janbjorge/pgqueuer/issues
Project-URL: Repository, https://github.com/janbjorge/pgqueuer/
Classifier: Development Status :: 5 - Production/Stable
Classifier: Environment :: Web Environment
Classifier: Framework :: AsyncIO
Classifier: Intended Audience :: Developers
Classifier: License :: OSI Approved :: MIT License
Classifier: Natural Language :: English
Classifier: Operating System :: OS Independent
Classifier: Programming Language :: Python :: 3.10
Classifier: Programming Language :: Python :: 3.11
Classifier: Programming Language :: Python :: 3.12
Classifier: Programming Language :: Python :: 3.13
Classifier: Programming Language :: Python :: 3.14
Classifier: Programming Language :: Python
Classifier: Topic :: Database
Classifier: Topic :: Software Development :: Libraries :: Python Modules
Classifier: Topic :: Utilities
Classifier: Topic :: System :: Distributed Computing
Requires-Python: >=3.10
License-File: LICENSE
Requires-Dist: anyio>=4.0
Requires-Dist: croniter>=5.0.1
Requires-Dist: pydantic-settings>=2.6.1
Requires-Dist: pydantic>=2.0.0
Requires-Dist: tabulate>=0.9.0
Requires-Dist: typer>=0.15.1
Requires-Dist: uvloop>=0.22.0; sys_platform != "win32"
Requires-Dist: async-timeout>=5.0.1
Provides-Extra: asyncpg
Requires-Dist: asyncpg>=0.30.0; extra == "asyncpg"
Provides-Extra: psycopg
Requires-Dist: psycopg>=3.2.0; extra == "psycopg"
Provides-Extra: logfire
Requires-Dist: logfire>=3.0.0; extra == "logfire"
Provides-Extra: sentry
Requires-Dist: sentry-sdk>=2.0.0; extra == "sentry"
Provides-Extra: dev
Requires-Dist: async-timeout>=4.0.3; extra == "dev"
Requires-Dist: asyncpg; extra == "dev"
Requires-Dist: asyncpg-stubs; extra == "dev"
Requires-Dist: fastapi; extra == "dev"
Requires-Dist: flask; extra == "dev"
Requires-Dist: httpx; extra == "dev"
Requires-Dist: icecream>=2.1.3; extra == "dev"
Requires-Dist: mypy; extra == "dev"
Requires-Dist: mypy-extensions; extra == "dev"
Requires-Dist: psycopg>=3.2.0; extra == "dev"
Requires-Dist: pytest; extra == "dev"
Requires-Dist: pytest-asyncio; extra == "dev"
Requires-Dist: pytest-mock>=3.14.0; extra == "dev"
Requires-Dist: pytest-timeout>=2.3.1; extra == "dev"
Requires-Dist: ruff; extra == "dev"
Requires-Dist: tqdm; extra == "dev"
Requires-Dist: types-croniter; extra == "dev"
Requires-Dist: types-tabulate; extra == "dev"
Requires-Dist: uvicorn; extra == "dev"
Requires-Dist: time-machine>=2.16.0; extra == "dev"
Requires-Dist: testcontainers>=4.12.0; extra == "dev"
Provides-Extra: docs
Requires-Dist: myst-parser; extra == "docs"
Requires-Dist: sphinx; extra == "docs"
Requires-Dist: sphinx-rtd-theme; extra == "docs"
Requires-Dist: sphinxcontrib-mermaid; extra == "docs"
Dynamic: license-file
